bindle/__about__.py
bindle/__init__.py
bindle/__main__.py
bindle/extensions.py
bindle/plot.py
bindle/stats.py
bindle/utils.py
bindle/.jupyter/desktop-workspaces/default-37a8.jupyterlab-workspace
bindle/cli/__init__.py
bindle-0.0.3.dist-info/METADATA
bindle-0.0.3.dist-info/WHEEL
bindle-0.0.3.dist-info/entry_points.txt
bindle-0.0.3.dist-info/RECORD
