Metadata-Version: 2.3
Name: bindle
Version: 0.0.3
Summary: My blanket stick.
Project-URL: Documentation, https://github.com/fioccajohn/bindle#readme
Project-URL: Issues, https://github.com/fioccajohn/bindle/issues
Project-URL: Source, https://github.com/fioccajohn/bindle
Author-email: John Fiocca <fioccajohn@gmail.com>
Classifier: Development Status :: 4 - Beta
Classifier: Programming Language :: Python
Classifier: Programming Language :: Python :: 3.8
Classifier: Programming Language :: Python :: 3.9
Classifier: Programming Language :: Python :: 3.10
Classifier: Programming Language :: Python :: 3.11
Classifier: Programming Language :: Python :: 3.12
Classifier: Programming Language :: Python :: Implementation :: CPython
Classifier: Programming Language :: Python :: Implementation :: PyPy
Requires-Python: >=3.8
Requires-Dist: click
Requires-Dist: ipython
Requires-Dist: jupyterlab
Requires-Dist: keyring
Requires-Dist: matplotlib
Requires-Dist: numpy
Requires-Dist: pandas
Requires-Dist: pandas-gbq
Requires-Dist: pyyaml
Requires-Dist: scikit-learn
Requires-Dist: scipy
Requires-Dist: seaborn
Requires-Dist: statsmodels
